README.rst
linux_setup.py
pywintypes.py
setup.py
test_win32api.py
test_win32crypt.py
test_win32event.py
test_win32file.py
test_win32gui.py
test_win32guistruct.py
test_win32inet.py
test_win32net.py
test_win32pipe.py
test_win32rcparser.py
test_win32timezone.py
test_win32trace.py
test_win32wnet.py
timer.py
win2kras.py
win32api.py
win32clipboard.py
win32clipboardDemo.py
win32clipboard_bitmapdemo.py
win32comport_demo.py
win32con.py
win32console.py
win32console_demo.py
win32cred.py
win32cred_demo.py
win32crypt.py
win32cryptcon.py
win32event.py
win32evtlog.py
win32file.py
win32gui.py
win32gui_demo.py
win32gui_devicenotify.py
win32gui_dialog.py
win32gui_menu.py
win32gui_struct.py
win32gui_taskbar.py
win32help.py
win32inet.py
win32inetcon.py
win32job.py
win32lz.py
win32net.py
win32netcon.py
win32netdemo.py
win32pdh.py
win32pdhquery.py
win32pdhutil.py
win32pipe.py
win32print.py
win32process.py
win32profile.py
win32ras.py
win32rcparser.py
win32rcparser_demo.py
win32security.py
win32service.py
win32servicedemo.py
win32serviceutil.py
win32timezone.py
win32trace.py
win32traceutil.py
win32transaction.py
win32ts.py
win32ts_logoff_disconnected.py
win32verstamp.py
win32wnet.py
winerror.py
winioctlcon.py
winnetwk.py
winnt.py
winperf.py
winprocess.py
winxpgui.py
winxptheme.py
bars/__init__.py
bars/__main__.py
bars/_bars.py
bars/_bars_gui.py
bars/_bars_notebook.py
bars/_bars_pandas.py
bars/_main.py
bars/_monitor.py
bars/_utils.py
bars/_version.py
bars/auto.py
bars/autonotebook.py
bars/cli.py
bars/gui.py
bars/notebook.py
bars/std.py
bars/utils.py
bars/bars/__init__.py
bars/bars/__main__.py
bars/bars/_bars.py
bars/bars/_bars_gui.py
bars/bars/_bars_notebook.py
bars/bars/_bars_pandas.py
bars/bars/_main.py
bars/bars/_monitor.py
bars/bars/_utils.py
bars/bars/_version.py
bars/bars/auto.py
bars/bars/autonotebook.py
bars/bars/cli.py
bars/bars/gui.py
bars/bars/notebook.py
bars/bars/std.py
bars/bars/utils.py
chatterbot/__init__.py
chatterbot/__main__.py
chatterbot/adapters.py
os_sys_linux.egg-info/PKG-INFO
os_sys_linux.egg-info/SOURCES.txt
os_sys_linux.egg-info/dependency_links.txt
os_sys_linux.egg-info/entry_points.txt
os_sys_linux.egg-info/requires.txt
os_sys_linux.egg-info/top_level.txt
